{"cameraMode":{"drawMode":0,"name":"Shaded","section":"Shading Mode"},"sceneLighting":true,"audioPlay":false,"sceneViewState":{"m_AlwaysRefresh":false,"showFog":true,"showSkybox":true,"showFlares":true,"showImageEffects":true,"showParticleSystems":true,"showVisualEffectGraphs":true,"m_FxEnabled":true},"in2DMode":false,"pivot":{"x":272.477294921875,"y":150.39710998535157,"z":13.283111572265625},"rotation":{"x":0.06894417852163315,"y":0.005985659081488848,"z":-0.0004137750656809658,"w":0.9976024031639099},"size":176.32864379882813,"orthographic":false}